{
  "conflicting": {
  },
  "long_description": "= DESCRIPTION:\n\n= REQUIREMENTS:\n\n= ATTRIBUTES:\n\n= USAGE:\n\n",
  "description": "Installs and configures PHP",
  "providing": {
  },
  "recipes": {
  },
  "maintainer": "Evolving Web Inc",
  "attributes": {
  },
  "replacing": {
  },
  "dependencies": {
    "graphviz": [

    ],
    "apt": [

    ]
  },
  "maintainer_email": "jeff@evolvingweb.ca",
  "groupings": {
  },
  "recommendations": {
  },
  "platforms": {
  },
  "version": "0.0.1",
  "license": "All rights reserved",
  "name": "php",
  "suggestions": {
  }
}